mufem.cpython-312-x86_64-linux-gnu.so
mufem/__init__.py
mufem/case.py
mufem/geometry.nm
mufem/mufem.so
mufem/bin/catalyst_replay
mufem/bin/cmpfillin
mufem/bin/conduit_adjset_validate
mufem/bin/conduit_blueprint_verify
mufem/bin/conduit_generate_data
mufem/bin/conduit_generate_data_mpi
mufem/bin/conduit_relay_entangle.py
mufem/bin/conduit_relay_io_convert
mufem/bin/conduit_relay_io_ls
mufem/bin/conduit_relay_node_viewer
mufem/bin/conduit_staging
mufem/bin/conduit_staging.json
mufem/bin/conduit_staging.sh
mufem/bin/csrcnv
mufem/bin/event_rpcgen.py
mufem/bin/gpmetis
mufem/bin/graphchk
mufem/bin/h5cc
mufem/bin/h5clear
mufem/bin/h5copy
mufem/bin/h5debug
mufem/bin/h5delete
mufem/bin/h5diff
mufem/bin/h5dump
mufem/bin/h5format_convert
mufem/bin/h5hlcc
mufem/bin/h5import
mufem/bin/h5jam
mufem/bin/h5ls
mufem/bin/h5mkgrp
mufem/bin/h5pcc
mufem/bin/h5perf
mufem/bin/h5perf_serial
mufem/bin/h5repack
mufem/bin/h5repart
mufem/bin/h5stat
mufem/bin/h5unjam
mufem/bin/h5watch
mufem/bin/hwloc-annotate
mufem/bin/hwloc-bind
mufem/bin/hwloc-calc
mufem/bin/hwloc-compress-dir
mufem/bin/hwloc-diff
mufem/bin/hwloc-distrib
mufem/bin/hwloc-gather-cpuid
mufem/bin/hwloc-gather-topology
mufem/bin/hwloc-info
mufem/bin/hwloc-ls
mufem/bin/hwloc-patch
mufem/bin/hwloc-ps
mufem/bin/lstopo
mufem/bin/lstopo-no-graphics
mufem/bin/m2gmetis
mufem/bin/mpiCC
mufem/bin/mpic++
mufem/bin/mpicc
mufem/bin/mpicxx
mufem/bin/mpiexec
mufem/bin/mpif77
mufem/bin/mpif90
mufem/bin/mpifort
mufem/bin/mpirun
mufem/bin/mpmetis
mufem/bin/ndmetis
mufem/bin/ompi_info
mufem/bin/opal_wrapper
mufem/bin/oshrun
mufem/bin/palloc
mufem/bin/parallel_python.sh
mufem/bin/pattrs
mufem/bin/pctrl
mufem/bin/pevent
mufem/bin/ph5diff
mufem/bin/plookup
mufem/bin/pm_dglpart
mufem/bin/pm_mtest
mufem/bin/pm_parmetis
mufem/bin/pm_pometis
mufem/bin/pm_ptest
mufem/bin/pmix_info
mufem/bin/pmixcc
mufem/bin/pps
mufem/bin/pquery
mufem/bin/prte
mufem/bin/prte_info
mufem-0.0.2.dist-info/METADATA
mufem-0.0.2.dist-info/WHEEL
mufem-0.0.2.dist-info/top_level.txt
mufem-0.0.2.dist-info/RECORD
